{
    "Ar36": {
        "error": 0.00014806405521563618, 
        "fit": "previous", 
        "references": [
            {
                "exclude": false, 
                "record_id": "bc-02-J-436"
            }
        ], 
        "value": -0.007145101145314121
    }, 
    "Ar37": {
        "error": 0.004994039542394009, 
        "fit": "previous", 
        "references": [
            {
                "exclude": false, 
                "record_id": "bc-02-J-436"
            }
        ], 
        "value": -0.006553522634825622
    }, 
    "Ar38": {
        "error": 0.002215102964600314, 
        "fit": "previous", 
        "references": [
            {
                "exclude": false, 
                "record_id": "bc-02-J-436"
            }
        ], 
        "value": -0.00412245735087537
    }, 
    "Ar39": {
        "error": 0.008580175572707007, 
        "fit": "previous", 
        "references": [
            {
                "exclude": false, 
                "record_id": "bc-02-J-436"
            }
        ], 
        "value": -0.07565195345271872
    }, 
    "Ar40": {
        "error": 0.02975802018065898, 
        "fit": "previous", 
        "references": [
            {
                "exclude": false, 
                "record_id": "bc-02-J-436"
            }
        ], 
        "value": -3.0653078916593453
    }, 
    "PM41": {
        "error": 0.060984464042433774, 
        "fit": "previous", 
        "references": [
            {
                "exclude": false, 
                "record_id": "bc-02-J-436"
            }
        ], 
        "value": 0.01254018666460921
    }
}