{
    "Ar36": {
        "error": 0.00023059645215860506, 
        "fit": "previous", 
        "references": [
            {
                "exclude": false, 
                "record_id": "bc-02-J-752"
            }
        ], 
        "value": 0.010910802345943214
    }, 
    "Ar37": {
        "error": 0.0049957945776163476, 
        "fit": "previous", 
        "references": [
            {
                "exclude": false, 
                "record_id": "bc-02-J-752"
            }
        ], 
        "value": 0.05688540291030851
    }, 
    "Ar38": {
        "error": 0.002245527383399318, 
        "fit": "previous", 
        "references": [
            {
                "exclude": false, 
                "record_id": "bc-02-J-752"
            }
        ], 
        "value": 0.009493349183784278
    }, 
    "Ar39": {
        "error": 0.009036061080844942, 
        "fit": "previous", 
        "references": [
            {
                "exclude": false, 
                "record_id": "bc-02-J-752"
            }
        ], 
        "value": 0.016658006447151708
    }, 
    "Ar40": {
        "error": 0.008868247875207558, 
        "fit": "previous", 
        "references": [
            {
                "exclude": false, 
                "record_id": "bc-02-J-752"
            }
        ], 
        "value": 2.2414469518626263
    }, 
    "Ar41": {
        "error": 0.003450109421560703, 
        "fit": "previous", 
        "references": [
            {
                "exclude": false, 
                "record_id": "bc-02-J-752"
            }
        ], 
        "value": 0.009566334707630922
    }
}