{
    "Ar36": {
        "error": 0.00015265396043031388, 
        "filter_outliers_dict": {
            "filter_outliers": true, 
            "iterations": 1, 
            "std_devs": 2
        }, 
        "fit": "Parabolic", 
        "value": 0.003529802495056068
    }, 
    "Ar37": {
        "error": 0.004897995944002104, 
        "filter_outliers_dict": {
            "filter_outliers": true, 
            "iterations": 1, 
            "std_devs": 2
        }, 
        "fit": "linear", 
        "value": 0.018265458913886787
    }, 
    "Ar38": {
        "error": 0.002094311030207827, 
        "filter_outliers_dict": {
            "filter_outliers": true, 
            "iterations": 1, 
            "std_devs": 2
        }, 
        "fit": "linear", 
        "value": -0.023115758422726805
    }, 
    "Ar39": {
        "error": 0.008897857115199753, 
        "filter_outliers_dict": {
            "filter_outliers": true, 
            "iterations": 1, 
            "std_devs": 2
        }, 
        "fit": "Parabolic", 
        "value": -0.05932044763308589
    }, 
    "Ar40": {
        "error": 0.006857257567112671, 
        "filter_outliers_dict": {
            "filter_outliers": true, 
            "iterations": 1, 
            "std_devs": 2
        }, 
        "fit": "Parabolic", 
        "value": 0.10881607839333783
    }, 
    "PM41": {
        "error": 0.06199437995706807, 
        "filter_outliers_dict": {
            "filter_outliers": false, 
            "iterations": 1, 
            "std_devs": 2
        }, 
        "fit": "linear", 
        "value": -0.17556173381798956
    }
}