{
    "AX": {
        "error": 0.0054732747772428475, 
        "filter_outliers_dict": {
            "filter_outliers": true, 
            "iterations": 1, 
            "std_devs": 2
        }, 
        "fit": "average", 
        "value": -0.049174219090744944
    }, 
    "CDD": {
        "error": 1.670279163859035e-05, 
        "filter_outliers_dict": {
            "filter_outliers": true, 
            "iterations": 1, 
            "std_devs": 10
        }, 
        "fit": "average", 
        "value": 0.0002046009135476452
    }, 
    "H1": {
        "error": 0.003853974619895247, 
        "filter_outliers_dict": {
            "filter_outliers": true, 
            "iterations": 1, 
            "std_devs": 2
        }, 
        "fit": "average", 
        "value": 0.11794554390621032
    }, 
    "H2": {
        "error": 0.0032166974351919586, 
        "filter_outliers_dict": {
            "filter_outliers": true, 
            "iterations": 1, 
            "std_devs": 2
        }, 
        "fit": "average", 
        "value": -0.04334789616923904
    }, 
    "L1": {
        "error": 0.001967672688368391, 
        "filter_outliers_dict": {
            "filter_outliers": true, 
            "iterations": 1, 
            "std_devs": 2
        }, 
        "fit": "average", 
        "value": -0.021976605713219636
    }, 
    "L2": {
        "error": 0.004212389874468263, 
        "filter_outliers_dict": {
            "filter_outliers": true, 
            "iterations": 1, 
            "std_devs": 2
        }, 
        "fit": "average", 
        "value": -0.023177468503089556
    }
}