{
    "AX": {
        "error": 0.004754433094578103, 
        "filter_outliers_dict": {
            "filter_outliers": true, 
            "iterations": 1, 
            "std_devs": 2
        }, 
        "fit": "average", 
        "value": 0.04626187825977163
    }, 
    "CDD": {
        "error": 1.640768566102143e-05, 
        "filter_outliers_dict": {
            "filter_outliers": true, 
            "iterations": 1, 
            "std_devs": 10
        }, 
        "fit": "average", 
        "value": 0.00020321972652355367
    }, 
    "H1": {
        "error": 0.003916794772440614, 
        "filter_outliers_dict": {
            "filter_outliers": true, 
            "iterations": 1, 
            "std_devs": 2
        }, 
        "fit": "average", 
        "value": 0.10800341183128268
    }, 
    "H2": {
        "error": 0.002632758351875053, 
        "filter_outliers_dict": {
            "filter_outliers": true, 
            "iterations": 1, 
            "std_devs": 2
        }, 
        "fit": "average", 
        "value": -0.32077853564551195
    }, 
    "L1": {
        "error": 0.0016293758102733206, 
        "filter_outliers_dict": {
            "filter_outliers": true, 
            "iterations": 1, 
            "std_devs": 2
        }, 
        "fit": "average", 
        "value": -0.23295873656580707
    }, 
    "L2": {
        "error": 0.0043971197110240804, 
        "filter_outliers_dict": {
            "filter_outliers": true, 
            "iterations": 1, 
            "std_devs": 2
        }, 
        "fit": "average", 
        "value": -0.009323499198382558
    }
}