{
    "AX": {
        "error": 0.004717095651985557, 
        "filter_outliers_dict": {
            "filter_outliers": true, 
            "iterations": 1, 
            "std_devs": 2
        }, 
        "fit": "average", 
        "value": -0.0841276700434901
    }, 
    "CDD": {
        "error": 1.5250434970149232e-05, 
        "filter_outliers_dict": {
            "filter_outliers": true, 
            "iterations": 1, 
            "std_devs": 10
        }, 
        "fit": "average", 
        "value": 0.00014390323255554
    }, 
    "H1": {
        "error": 0.003469307088551036, 
        "filter_outliers_dict": {
            "filter_outliers": true, 
            "iterations": 1, 
            "std_devs": 2
        }, 
        "fit": "average", 
        "value": -0.018002356226036232
    }, 
    "H2": {
        "error": 0.006023951215271174, 
        "filter_outliers_dict": {
            "filter_outliers": true, 
            "iterations": 1, 
            "std_devs": 2
        }, 
        "fit": "average", 
        "value": -0.2038441607879823
    }, 
    "L1": {
        "error": 0.0018781295733064113, 
        "filter_outliers_dict": {
            "filter_outliers": true, 
            "iterations": 1, 
            "std_devs": 2
        }, 
        "fit": "average", 
        "value": -0.02088203854021155
    }, 
    "L2": {
        "error": 0.004348773882230842, 
        "filter_outliers_dict": {
            "filter_outliers": true, 
            "iterations": 1, 
            "std_devs": 2
        }, 
        "fit": "average", 
        "value": -0.021717954731417587
    }
}