{
    "Ar36": {
        "error": 0.0003478163932919162, 
        "filter_outliers_dict": {
            "filter_outliers": true, 
            "iterations": 1, 
            "std_devs": 10
        }, 
        "fit": "Parabolic", 
        "fn": 400, 
        "include_baseline_error": false, 
        "n": 400, 
        "value": 0.024634021216889387
    }, 
    "Ar37": {
        "error": 0.005028427758907658, 
        "filter_outliers_dict": {
            "filter_outliers": true, 
            "iterations": 1, 
            "std_devs": 2
        }, 
        "fit": "Linear", 
        "fn": 386, 
        "include_baseline_error": false, 
        "n": 400, 
        "value": 0.035322958768604605
    }, 
    "Ar38": {
        "error": 0.002111994404536211, 
        "filter_outliers_dict": {
            "filter_outliers": true, 
            "iterations": 1, 
            "std_devs": 2
        }, 
        "fit": "Linear", 
        "fn": 376, 
        "include_baseline_error": false, 
        "n": 400, 
        "value": 0.7321446261381731
    }, 
    "Ar39": {
        "error": 0.013773252387595723, 
        "filter_outliers_dict": {
            "filter_outliers": true, 
            "iterations": 1, 
            "std_devs": 2
        }, 
        "fit": "Parabolic", 
        "fn": 386, 
        "include_baseline_error": false, 
        "n": 400, 
        "value": 57.97916923174424
    }, 
    "Ar40": {
        "error": 0.03504643506470668, 
        "filter_outliers_dict": {
            "filter_outliers": true, 
            "iterations": 1, 
            "std_devs": 2
        }, 
        "fit": "Parabolic", 
        "fn": 384, 
        "include_baseline_error": false, 
        "n": 400, 
        "value": 723.198702438725
    }, 
    "Ar41": {
        "error": 0.002894876430286238, 
        "filter_outliers_dict": {
            "filter_outliers": true, 
            "iterations": 1, 
            "std_devs": 2
        }, 
        "fit": "Average", 
        "fn": 385, 
        "include_baseline_error": false, 
        "n": 400, 
        "value": -0.14456001983157227
    }, 
    "reviewed": true
}