{
    "Ar36": {
        "error": 0.0003568883155521544, 
        "filter_outliers_dict": {
            "filter_outliers": true, 
            "iterations": 1, 
            "std_devs": 2
        }, 
        "fit": "Parabolic", 
        "value": 0.034662357261842205
    }, 
    "Ar37": {
        "error": 0.0052860385318004985, 
        "filter_outliers_dict": {
            "filter_outliers": true, 
            "iterations": 1, 
            "std_devs": 2
        }, 
        "fit": "linear", 
        "value": 0.045614045082808995
    }, 
    "Ar38": {
        "error": 0.002188198471420732, 
        "filter_outliers_dict": {
            "filter_outliers": true, 
            "iterations": 1, 
            "std_devs": 2
        }, 
        "fit": "linear", 
        "value": 0.7226962933240253
    }, 
    "Ar39": {
        "error": 0.012658867010682976, 
        "filter_outliers_dict": {
            "filter_outliers": true, 
            "iterations": 1, 
            "std_devs": 2
        }, 
        "fit": "Parabolic", 
        "value": 57.21971509359934
    }, 
    "Ar40": {
        "error": 0.03290052684947482, 
        "filter_outliers_dict": {
            "filter_outliers": true, 
            "iterations": 1, 
            "std_devs": 2
        }, 
        "fit": "Parabolic", 
        "value": 716.2257519435963
    }, 
    "Ar41": {
        "error": 0.006010082190334431, 
        "filter_outliers_dict": {
            "filter_outliers": true, 
            "iterations": 1, 
            "std_devs": 2
        }, 
        "fit": "linear", 
        "value": -0.14240172622850683
    }
}