{
    "Ar36": {
        "error": 0.00038925060519668053, 
        "filter_outliers_dict": {
            "filter_outliers": true, 
            "iterations": 1, 
            "std_devs": 2
        }, 
        "fit": "Parabolic", 
        "value": 0.045604474816672874
    }, 
    "Ar37": {
        "error": 0.004885680704509929, 
        "filter_outliers_dict": {
            "filter_outliers": true, 
            "iterations": 1, 
            "std_devs": 2
        }, 
        "fit": "linear", 
        "value": 0.04612491939188697
    }, 
    "Ar38": {
        "error": 0.002288440338694596, 
        "filter_outliers_dict": {
            "filter_outliers": true, 
            "iterations": 1, 
            "std_devs": 2
        }, 
        "fit": "linear", 
        "value": 1.2237464283508048
    }, 
    "Ar39": {
        "error": 0.01561178493923068, 
        "filter_outliers_dict": {
            "filter_outliers": true, 
            "iterations": 1, 
            "std_devs": 2
        }, 
        "fit": "Parabolic", 
        "value": 95.78110504472095
    }, 
    "Ar40": {
        "error": 0.04670020729145366, 
        "filter_outliers_dict": {
            "filter_outliers": true, 
            "iterations": 1, 
            "std_devs": 2
        }, 
        "fit": "Parabolic", 
        "value": 1194.4640537240566
    }, 
    "Ar41": {
        "error": 0.0034185742439552446, 
        "filter_outliers_dict": {
            "filter_outliers": true, 
            "iterations": 1, 
            "std_devs": 2
        }, 
        "fit": "linear", 
        "value": 0.006987164759108277
    }
}