{
    "Ar36": {
        "error": 0.00028479666160358564, 
        "filter_outliers_dict": {
            "filter_outliers": true, 
            "iterations": 1, 
            "std_devs": 2
        }, 
        "fit": "Parabolic", 
        "value": 0.02395960524981519
    }, 
    "Ar37": {
        "error": 0.005012146302120055, 
        "filter_outliers_dict": {
            "filter_outliers": true, 
            "iterations": 1, 
            "std_devs": 2
        }, 
        "fit": "linear", 
        "value": 0.02672640306040173
    }, 
    "Ar38": {
        "error": 0.0022138586728758453, 
        "filter_outliers_dict": {
            "filter_outliers": true, 
            "iterations": 1, 
            "std_devs": 2
        }, 
        "fit": "linear", 
        "value": 0.7626481543827403
    }, 
    "Ar39": {
        "error": 0.013613834637309625, 
        "filter_outliers_dict": {
            "filter_outliers": true, 
            "iterations": 1, 
            "std_devs": 2
        }, 
        "fit": "Parabolic", 
        "value": 59.86455421019156
    }, 
    "Ar40": {
        "error": 0.050465744649144384, 
        "filter_outliers_dict": {
            "filter_outliers": true, 
            "iterations": 1, 
            "std_devs": 2
        }, 
        "fit": "Parabolic", 
        "value": 745.7529639987124
    }, 
    "PM41": {
        "error": 0.06782925143853794, 
        "filter_outliers_dict": {
            "filter_outliers": false, 
            "iterations": 1, 
            "std_devs": 2
        }, 
        "fit": "linear", 
        "value": -0.15369889905342837
    }
}