{
    "Ar36": {
        "error": 0.0004606963138797726, 
        "filter_outliers_dict": {
            "filter_outliers": true, 
            "iterations": 1, 
            "std_devs": 10
        }, 
        "fit": "Parabolic", 
        "fn": 400, 
        "include_baseline_error": false, 
        "n": 400, 
        "value": 0.045085647674960275
    }, 
    "Ar37": {
        "error": 0.005242829483687255, 
        "filter_outliers_dict": {
            "filter_outliers": true, 
            "iterations": 1, 
            "std_devs": 2
        }, 
        "fit": "Linear", 
        "fn": 381, 
        "include_baseline_error": false, 
        "n": 400, 
        "value": 0.037591083679021364
    }, 
    "Ar38": {
        "error": 0.0026416936854406587, 
        "filter_outliers_dict": {
            "filter_outliers": true, 
            "iterations": 1, 
            "std_devs": 2
        }, 
        "fit": "Linear", 
        "fn": 383, 
        "include_baseline_error": false, 
        "n": 400, 
        "value": 1.305288500521464
    }, 
    "Ar39": {
        "error": 0.01654360083124347, 
        "filter_outliers_dict": {
            "filter_outliers": true, 
            "iterations": 1, 
            "std_devs": 2
        }, 
        "fit": "Parabolic", 
        "fn": 386, 
        "include_baseline_error": false, 
        "n": 400, 
        "value": 95.83430126605384
    }, 
    "Ar40": {
        "error": 0.05061516058507707, 
        "filter_outliers_dict": {
            "filter_outliers": true, 
            "iterations": 1, 
            "std_devs": 2
        }, 
        "fit": "Parabolic", 
        "fn": 384, 
        "include_baseline_error": false, 
        "n": 400, 
        "value": 1196.4813206230983
    }, 
    "Ar41": {
        "error": 0.0016111319706441142, 
        "filter_outliers_dict": {
            "filter_outliers": true, 
            "iterations": 1, 
            "std_devs": 2
        }, 
        "fit": "Average", 
        "fn": 382, 
        "include_baseline_error": false, 
        "n": 400, 
        "value": 0.0016671313040786794
    }, 
    "reviewed": true
}