{
    "Ar36": {
        "error": 0.0004248206485108732, 
        "filter_outliers_dict": {
            "filter_outliers": true, 
            "iterations": 1, 
            "std_devs": 2
        }, 
        "fit": "Parabolic", 
        "value": 0.044596688773657495
    }, 
    "Ar37": {
        "error": 0.004985476436686457, 
        "filter_outliers_dict": {
            "filter_outliers": true, 
            "iterations": 1, 
            "std_devs": 2
        }, 
        "fit": "linear", 
        "value": 0.03972638480698774
    }, 
    "Ar38": {
        "error": 0.002253546707601166, 
        "filter_outliers_dict": {
            "filter_outliers": true, 
            "iterations": 1, 
            "std_devs": 2
        }, 
        "fit": "linear", 
        "value": 1.3096550244313883
    }, 
    "Ar39": {
        "error": 0.015947278899223958, 
        "filter_outliers_dict": {
            "filter_outliers": true, 
            "iterations": 1, 
            "std_devs": 2
        }, 
        "fit": "Parabolic", 
        "value": 95.71720157279273
    }, 
    "Ar40": {
        "error": 0.04717121708068186, 
        "filter_outliers_dict": {
            "filter_outliers": true, 
            "iterations": 1, 
            "std_devs": 2
        }, 
        "fit": "Parabolic", 
        "value": 1195.14885155244
    }, 
    "Ar41": {
        "error": 0.0035531091404449105, 
        "filter_outliers_dict": {
            "filter_outliers": true, 
            "iterations": 1, 
            "std_devs": 2
        }, 
        "fit": "linear", 
        "value": 0.009898385982967306
    }
}