{
    "AX": {
        "error": 0.004456885796129663, 
        "filter_outliers_dict": {
            "filter_outliers": true, 
            "iterations": 1, 
            "std_devs": 2
        }, 
        "fit": "average", 
        "value": -0.07044330215289792
    }, 
    "CDD": {
        "error": 4.212101986268782e-06, 
        "filter_outliers_dict": {
            "filter_outliers": true, 
            "iterations": 1, 
            "std_devs": 10
        }, 
        "fit": "average", 
        "value": 1.2552203137223518e-05
    }, 
    "H1": {
        "error": 0.00447273421786252, 
        "filter_outliers_dict": {
            "filter_outliers": true, 
            "iterations": 1, 
            "std_devs": 2
        }, 
        "fit": "average", 
        "value": 0.11461939876033668
    }, 
    "H2": {
        "error": 0.004741334639033932, 
        "filter_outliers_dict": {
            "filter_outliers": true, 
            "iterations": 1, 
            "std_devs": 2
        }, 
        "fit": "average", 
        "value": -0.1990787245599912
    }, 
    "L1": {
        "error": 0.0017856588492876943, 
        "filter_outliers_dict": {
            "filter_outliers": true, 
            "iterations": 1, 
            "std_devs": 2
        }, 
        "fit": "average", 
        "value": -0.02532566609773165
    }, 
    "L2": {
        "error": 0.003716085864592835, 
        "filter_outliers_dict": {
            "filter_outliers": true, 
            "iterations": 1, 
            "std_devs": 2
        }, 
        "fit": "average", 
        "value": -0.021116976900076082
    }
}